easystuff/__init__.py
easystuff/easystuff.py
easystuff-0.0.4.dist-info/LICENCE
easystuff-0.0.4.dist-info/METADATA
easystuff-0.0.4.dist-info/WHEEL
easystuff-0.0.4.dist-info/top_level.txt
easystuff-0.0.4.dist-info/RECORD
