Metadata-Version: 2.1
Name: easystuff
Version: 0.0.4
Summary: A small package for downloading and copying files with ease.
Home-page: https://github.com/RemyIsCool/easystuff
Author: remydev
Author-email: remyrfouquette@gmail.com
License: UNKNOWN
Project-URL: Bug Tracker, https://github.com/RemyIsCool/easystuff/issues
Platform: UNKNOWN
Classifier: Programming Language :: Python :: 3
Classifier: License :: OSI Approved :: MIT License
Classifier: Operating System :: OS Independent
Requires-Python: >=3.6
License-File: LICENCE
Requires-Dist: requests
